<?xml version="1.0" encoding="UTF-8"?>
<!DOCTYPE struts 
	PUBLIC "-//Apache Software Foundation//DTD Struts Configuration 2.0//EN"
	"http://struts.apache.org/dtds/struts-2.1.dtd" >
<struts>

	<package name="student" extends="struts-default" namespace="/student">
		<global-results>
			<result name="addLink">/WEB-INF/model/student/studentAdd.jsp</result>
			<result name="updateLink">/WEB-INF/model/student/studentUpdate.jsp</result>
			<result name="index" type="redirectAction">listStudent</result>
			<result name="input">/WEB-INF/model/student/student.jsp</result>
		</global-results>
		<action name="*Student" class="cn.gdpu.action.StudentAction" method="{1}"></action>
		<action name="fileUpload" class="cn.gdpu.action.FileUploadAction">
			<interceptor-ref name="fileUpload">
				<param name="allowedTypes">application/vnd.ms-excel,application/msword,application/octet-stream</param>
				<param name="maximumSize">4096000</param>
			</interceptor-ref>
			<interceptor-ref name="defaultStack"></interceptor-ref>
			<!-- Action中的savePath属性的值 -->
			<param name="savePath">/upload</param>
		</action>
	</package>

	<package name="admin" extends="struts-default" namespace="/admin">
		<global-results>
			<result name="addLink">/WEB-INF/model/admin/adminAdd.jsp</result>
			<result name="updateLink">/WEB-INF/model/admin/adminUpdate.jsp</result>
			<result name="index" type="redirectAction">listAdmin</result>
			<result name="input">/WEB-INF/model/admin/admin.jsp</result>
		</global-results>
		<action name="*Admin" class="cn.gdpu.action.AdminAction" method="{1}">
		</action>
	</package>

	<package name="leader" extends="struts-default" namespace="/leader">
		<global-results>
			<result name="addLink">/WEB-INF/model/leader/leaderAdd.jsp</result>
			<result name="updateLink">/WEB-INF/model/leader/leaderUpdate.jsp</result>
			<result name="index" type="redirectAction">listLeader</result>
			<result name="input">/WEB-INF/model/leader/leader.jsp</result>
		</global-results>
		<action name="*Leader" class="cn.gdpu.action.LeaderAction" method="{1}">
		</action>
	</package>
	
	<package name="duty" extends="struts-default" namespace="/duty">
		<global-results>
			<result name="addLink">/WEB-INF/model/duty/dutyAdd.jsp</result>
			<result name="updateLink">/WEB-INF/model/duty/dutyUpdate.jsp</result>
			<result name="index" type="redirectAction">listDuty</result>
			<result name="input">/WEB-INF/model/duty/duty.jsp</result>
		</global-results>
		<action name="*Duty" class="cn.gdpu.action.DutyAction" method="{1}">
		</action>
	</package>
	
	<package name="attendancte" extends="struts-default" namespace="/attendance">
		<global-results>
			<result name="success">/WEB-INF/model/attendance/attendance.jsp</result>
			<result name="error">/WEB-INF/model/attendance/attendance.jsp</result>
			<result name="addLink">/WEB-INF/model/attendance/attendanceAdd.jsp</result>
			<result name="updateLink">/WEB-INF/model/attendance/attendanceUpdate.jsp</result>
			<result name="index" type="redirectAction">listAttendance</result>
			<result name="input">/WEB-INF/model/attendance/attendance.jsp</result>
		</global-results>
		<action name="*Attendance" class="cn.gdpu.action.AttendanceAction" method="{1}">
		</action>
	</package>

</struts>    